ironic_prometheus_exporter/__init__.py
ironic_prometheus_exporter/messaging.py
ironic_prometheus_exporter/utils.py
ironic_prometheus_exporter/app/__init__.py
ironic_prometheus_exporter/app/exporter.py
ironic_prometheus_exporter/app/wsgi.py
ironic_prometheus_exporter/parsers/__init__.py
ironic_prometheus_exporter/parsers/descriptions.py
ironic_prometheus_exporter/parsers/header.py
ironic_prometheus_exporter/parsers/ipmi.py
ironic_prometheus_exporter/parsers/ironic.py
ironic_prometheus_exporter/parsers/redfish.py
ironic_prometheus_exporter/parsers/metrics_information/header.json
ironic_prometheus_exporter/parsers/metrics_information/ipmi.json
ironic_prometheus_exporter/parsers/metrics_information/redfish.json
ironic_prometheus_exporter/tests/__init__.py
ironic_prometheus_exporter/tests/test_descriptions.py
ironic_prometheus_exporter/tests/test_driver.py
ironic_prometheus_exporter/tests/test_header_parser.py
ironic_prometheus_exporter/tests/test_ipmi_parser.py
ironic_prometheus_exporter/tests/test_ironic_parser.py
ironic_prometheus_exporter/tests/test_redfish_parser.py
ironic_prometheus_exporter/tests/json_samples/expected_ironic_parser_entries.json
ironic_prometheus_exporter/tests/json_samples/notification-empty-node_name.json
ironic_prometheus_exporter/tests/json_samples/notification-header-with-none.json
ironic_prometheus_exporter/tests/json_samples/notification-header.json
ironic_prometheus_exporter/tests/json_samples/notification-ipmi-1.json
ironic_prometheus_exporter/tests/json_samples/notification-ipmi-2.json
ironic_prometheus_exporter/tests/json_samples/notification-ipmi-none-instance_uuid.json
ironic_prometheus_exporter/tests/json_samples/notification-ipmi-none-node_name.json
ironic_prometheus_exporter/tests/json_samples/notification-ironic.json
ironic_prometheus_exporter/tests/json_samples/notification-none-node_name.json
ironic_prometheus_exporter/tests/json_samples/notification-redfish-none-instance_uuid.json
ironic_prometheus_exporter-4.6.0.dist-info/AUTHORS
ironic_prometheus_exporter-4.6.0.dist-info/LICENSE
ironic_prometheus_exporter-4.6.0.dist-info/METADATA
ironic_prometheus_exporter-4.6.0.dist-info/WHEEL
ironic_prometheus_exporter-4.6.0.dist-info/entry_points.txt
ironic_prometheus_exporter-4.6.0.dist-info/pbr.json
ironic_prometheus_exporter-4.6.0.dist-info/top_level.txt
ironic_prometheus_exporter-4.6.0.dist-info/RECORD
