Metadata-Version: 2.1
Name: ironic-prometheus-exporter
Version: 4.6.0
Summary: Prometheus Exporter for Ironic Hardware Sensor data
Home-page: https://opendev.org/openstack/ironic-prometheus-exporter
Author: OpenStack
Author-email: openstack-discuss@lists.openstack.org
License: Apache-2
Classifier: Environment :: Console
Classifier: Environment :: OpenStack
Classifier: Intended Audience :: System Administrators
Classifier: Intended Audience :: Information Technology
Classifier: License :: OSI Approved :: Apache Software License
Classifier: Operating System :: OS Independent
Classifier: Programming Language :: Python
Classifier: Programming Language :: Python :: Implementation :: CPython
Classifier: Programming Language :: Python :: 3 :: Only
Classifier: Programming Language :: Python :: 3
Classifier: Programming Language :: Python :: 3.9
Classifier: Programming Language :: Python :: 3.10
Classifier: Programming Language :: Python :: 3.11
Requires-Python: >=3.9
License-File: LICENSE
License-File: AUTHORS
Requires-Dist: pbr >=6.0.0
Requires-Dist: stevedore >=1.20.0
Requires-Dist: oslo.messaging >=9.4.0
Requires-Dist: Flask >=1.0.0
Requires-Dist: prometheus-client >=0.6.0
